ctorrent/__init__.py
ctorrent/__main__.py
ctorrent/torrents.py
ctorrent/utils.py
ctorrent-0.0.4.dist-info/LICENSE
ctorrent-0.0.4.dist-info/METADATA
ctorrent-0.0.4.dist-info/WHEEL
ctorrent-0.0.4.dist-info/entry_points.txt
ctorrent-0.0.4.dist-info/top_level.txt
ctorrent-0.0.4.dist-info/RECORD
