Metadata-Version: 2.1
Name: ctorrent
Version: 0.0.4
Summary: Curses Torrent Browser
Home-page: https://github.com/tslight/ctorrent
Author: Toby Slight
Author-email: tslight@pm.me
License: UNKNOWN
Platform: UNKNOWN
Classifier: Programming Language :: Python :: 3
Classifier: License :: OSI Approved :: ISC License (ISCL)
Classifier: Operating System :: OS Independent
License-File: LICENSE
Requires-Dist: requests
Requires-Dist: ctable
